{
  "apps" : [
    {
      "beta" : false,
      "bundleIdentifier" : "app.App-Fair",
      "categories" : [

      ],
      "developerName" : "appfairz <appfairz@appfair.net>",
      "downloadURL" : "https://github.com/App-Fair/App/releases/download/0.8.84/App-Fair-macOS.zip",
      "fundingLinks" : [

      ],
      "homepage" : "https://appfair.app",
      "iconURL" : "https://github.com/App-Fair/App/releases/download/0.8.84/App-Fair.png",
      "localizedDescription" : "Open-source browser and installer for macOS apps and Homebrew casks",
      "metadataURL" : "https://github.com/App-Fair/App/releases/download/0.8.84/Info.plist#287f07041cc41ea4c4abc21479cf5d8d11761f6868698f62dfe930e1328f9566",
      "name" : "App Fair",
      "permissions" : [
        {
          "type" : "com.apple.security.network.client",
          "usageDescription" : "The App Fair uses the network to browse the available releases and install apps"
        },
        {
          "type" : "com.apple.security.files.user-selected.read-write",
          "usageDescription" : "The App Fair uses the local file system to install apps"
        },
        {
          "type" : "com.apple.security.temporary-exception.files.absolute-path.read-write",
          "usageDescription" : "The App Fair uses the local file system to install apps"
        },
        {
          "type" : "com.apple.security.network.server",
          "usageDescription" : "The App Fair acts as a server for checking for app updates"
        },
        {
          "type" : "com.apple.security.files.user-selected.executable",
          "usageDescription" : "The App Fair installs executable apps"
        }
      ],
      "readmeURL" : "https://github.com/App-Fair/App/releases/download/0.8.84/README.md#2e818c0471081243bb5e49364e7923152dcd8a36dcd5c596bd8fe699d74c76e1",
      "screenshotURLs" : [
        "https://github.com/App-Fair/App/releases/download/0.8.84/screenshot_00-mac-dark-3078x2044.png",
        "https://github.com/App-Fair/App/releases/download/0.8.84/screenshot_00-mac-dark-2864x1950.png",
        "https://github.com/App-Fair/App/releases/download/0.8.84/screenshot_00-mac-light-2454x1654.png",
        "https://github.com/App-Fair/App/releases/download/0.8.84/screenshot_01-mac-dark-2840x1848.png",
        "https://github.com/App-Fair/App/releases/download/0.8.84/screenshot_01-mac-light-2840x1848.png",
        "https://github.com/App-Fair/App/releases/download/0.8.84/screenshot_02-mac-dark-2450x1652.png",
        "https://github.com/App-Fair/App/releases/download/0.8.84/screenshot_02-mac-light-2450x1652.png",
        "https://github.com/App-Fair/App/releases/download/0.8.84/screenshot_03-mac-dark-2878x2120.png",
        "https://github.com/App-Fair/App/releases/download/0.8.84/screenshot_04-mac-1424x728.png",
        "https://github.com/App-Fair/App/releases/download/0.8.84/screenshot_05-mac-dark-1424x1038.png",
        "https://github.com/App-Fair/App/releases/download/0.8.84/screenshot_05-mac-light-1424x1038.png",
        "https://github.com/App-Fair/App/releases/download/0.8.84/screenshot_06-mac-dark-1424x1722.png"
      ],
      "sha256" : "6c147aa38b0a7634221d8b66072fc4ac87c2d4a552be331804727e98ec4d3ffb",
      "size" : 9417244,
      "stats" : {
        "coreSize" : 170672,
        "downloadCount" : 80,
        "impressionCount" : 26,
        "issueCount" : 5,
        "starCount" : 23,
        "viewCount" : 3,
        "watcherCount" : 3
      },
      "subtitle" : "Open-source browser and installer for macOS apps and Homebrew casks",
      "tintColor" : "1594E8",
      "version" : "0.8.84",
      "versionDate" : "2022-07-21T00:00:00Z",
      "versionDescription" : "**Full Changelog**: https://github.com/App-Fair/App/compare/0.8.83...0.8.84"
    },
    {
      "beta" : true,
      "bundleIdentifier" : "app.App-Title",
      "categories" : [

      ],
      "developerName" : "fair-ground action <fair-ground@users.noreply.github.com>",
      "downloadURL" : "https://github.com/App-Title/App/releases/download/0.0.1/App-Title-macOS.zip",
      "fundingLinks" : [

      ],
      "iconURL" : "https://github.com/App-Title/App/releases/download/0.0.1/App-Title.png",
      "localizedDescription" : "A very useful app indeed",
      "metadataURL" : "https://github.com/App-Title/App/releases/download/0.0.1/Info.plist#27abe8e41c39d7eb3bb457c705e3816ee80253ee373e57f7a9c6704d85b542c8",
      "name" : "App Title",
      "permissions" : [

      ],
      "readmeURL" : "https://github.com/App-Title/App/releases/download/0.0.1/README.md#5f665b7ecc017cdcd7917a881e68502b9062036dcc7caa1dddf81d644721debb",
      "sha256" : "cdee27f9a4108574041b293ae1483bd748186d61b74cb165f1e60a7b921a6f45",
      "size" : 2443924,
      "stats" : {
        "coreSize" : 170128,
        "downloadCount" : 6,
        "impressionCount" : 446,
        "issueCount" : 0,
        "starCount" : 0,
        "viewCount" : 61,
        "watcherCount" : 0
      },
      "subtitle" : "A very useful app indeed",
      "version" : "0.0.1",
      "versionDate" : "2022-05-19T00:00:00Z"
    },
    {
      "beta" : false,
      "bundleIdentifier" : "app.Blunder-Busq",
      "categories" : [

      ],
      "developerName" : "blunderbusq <blunderbusq@blunderbusq.app>",
      "downloadURL" : "https://github.com/Blunder-Busq/App/releases/download/0.1.7/Blunder-Busq-macOS.zip",
      "fundingLinks" : [

      ],
      "homepage" : "https://www.blunderbusq.app",
      "iconURL" : "https://github.com/Blunder-Busq/App/releases/download/0.1.7/Blunder-Busq.png",
      "localizedDescription" : "App for managing iOS devices",
      "metadataURL" : "https://github.com/Blunder-Busq/App/releases/download/0.1.7/Info.plist#eeacf8a384590ae1a8681f0a12a0562cc5ffddd7ad296886d77afd869cc0acb5",
      "name" : "Blunder Busq",
      "permissions" : [
        {
          "type" : "network.client",
          "usageDescription" : "This app needs to access the network in order to download apps"
        },
        {
          "type" : "device.usb",
          "usageDescription" : "This app needs to access USB connections to devices"
        },
        {
          "type" : "files.user-selected.read-only",
          "usageDescription" : "This app needs to read local files in order to load user-selected IPAs"
        }
      ],
      "readmeURL" : "https://github.com/Blunder-Busq/App/releases/download/0.1.7/README.md#3f5af5ae690752c4cdb38f3c2620a4c99e60f17d144edcec5a1f8ae1c5a34ba8",
      "screenshotURLs" : [
        "https://github.com/Blunder-Busq/App/releases/download/0.1.7/screenshot_01-mac-dark-2560x1884.png",
        "https://github.com/Blunder-Busq/App/releases/download/0.1.7/screenshot_01-mac-light-2560x1884.png"
      ],
      "sha256" : "4ec4bc454a71f12fa9abe0dd5ab3ec44d3d9fd2babd2e1c8fad514c1af907100",
      "size" : 4506286,
      "stats" : {
        "coreSize" : 170576,
        "downloadCount" : 29,
        "impressionCount" : 2884,
        "issueCount" : 0,
        "starCount" : 1,
        "viewCount" : 522,
        "watcherCount" : 1
      },
      "subtitle" : "App for managing iOS devices",
      "tintColor" : "587FE3",
      "version" : "0.1.7",
      "versionDate" : "2022-05-24T00:00:00Z",
      "versionDescription" : "**Full Changelog**: https://github.com/Blunder-Busq/App/compare/0.1.6...0.1.7"
    },
    {
      "beta" : true,
      "bundleIdentifier" : "app.Bon-Mot",
      "categories" : [

      ],
      "developerName" : "fairapps <fairapps@appfair.org>",
      "downloadURL" : "https://github.com/Bon-Mot/App/releases/download/0.2.34/Bon-Mot-macOS.zip",
      "fundingLinks" : [

      ],
      "iconURL" : "https://github.com/Bon-Mot/App/releases/download/0.2.34/Bon-Mot.png",
      "localizedDescription" : "Simple dictionary app",
      "metadataURL" : "https://github.com/Bon-Mot/App/releases/download/0.2.34/Info.plist#27abe8e41c39d7eb3bb457c705e3816ee80253ee373e57f7a9c6704d85b542c8",
      "name" : "Bon Mot",
      "permissions" : [
        {
          "type" : "com.apple.security.files.user-selected.read-only",
          "usageDescription" : "This app needs to read local files in order to load user-selected books"
        },
        {
          "type" : "com.apple.security.network.client",
          "usageDescription" : "This app needs to access the network in order to download books"
        }
      ],
      "readmeURL" : "https://github.com/Bon-Mot/App/releases/download/0.2.34/README.md#6aaa6d708dd87e0f287fcc67e14ce094575bb468f231c59a4341043ae9ff6708",
      "screenshotURLs" : [
        "https://github.com/Bon-Mot/App/releases/download/0.2.34/screenshot_01-mac-dark-mac-2024x1124.png",
        "https://github.com/Bon-Mot/App/releases/download/0.2.34/screenshot_01-mac-light-mac-2024x1124.png"
      ],
      "sha256" : "bb74a5996de9ddf235b4935021b14fc6151221a2e51a995e528d31b7b88af752",
      "size" : 2075091,
      "stats" : {
        "coreSize" : 102376,
        "downloadCount" : 26,
        "impressionCount" : 249,
        "issueCount" : 0,
        "starCount" : 1,
        "viewCount" : 9,
        "watcherCount" : 0
      },
      "subtitle" : "Simple dictionary app",
      "tintColor" : "A2845E",
      "version" : "0.2.34",
      "versionDate" : "2022-07-20T00:00:00Z",
      "versionDescription" : "**Full Changelog**: https://github.com/Bon-Mot/App/compare/0.2.33...0.2.34"
    },
    {
      "beta" : false,
      "bundleIdentifier" : "app.Cloud-Cuckoo",
      "categories" : [

      ],
      "developerName" : "fairapps <fairapps@appfair.org>",
      "downloadURL" : "https://github.com/Cloud-Cuckoo/App/releases/download/0.9.138/Cloud-Cuckoo-macOS.zip",
      "fundingLinks" : [

      ],
      "iconURL" : "https://github.com/Cloud-Cuckoo/App/releases/download/0.9.138/Cloud-Cuckoo.png",
      "localizedDescription" : "A whimsical game of excitement and delight",
      "metadataURL" : "https://github.com/Cloud-Cuckoo/App/releases/download/0.9.138/Info.plist#9ee02675dd5a50e712f300d7dabe9df6cac040892cab73f9fcafc8df7e147f5b",
      "name" : "Cloud Cuckoo",
      "permissions" : [

      ],
      "readmeURL" : "https://github.com/Cloud-Cuckoo/App/releases/download/0.9.138/README.md#14096a2fe25ad053f6fdc3f83a87eea9a207fccf6a1189f2481ab66a8be78f25",
      "screenshotURLs" : [
        "https://github.com/Cloud-Cuckoo/App/releases/download/0.9.138/screenshot_01-mac-dark-2024x1696.png",
        "https://github.com/Cloud-Cuckoo/App/releases/download/0.9.138/screenshot_01-mac-light-2024x1696.png",
        "https://github.com/Cloud-Cuckoo/App/releases/download/0.9.138/screenshot_03-mac-1714x522.png",
        "https://github.com/Cloud-Cuckoo/App/releases/download/0.9.138/screenshot_05-mac-1634x1040.png",
        "https://github.com/Cloud-Cuckoo/App/releases/download/0.9.138/screenshot_06-mac-1656x1560.png"
      ],
      "sha256" : "001abadfee686bae55ed8d43ab813b3bc389dca2aaa512e637dac998fe4d7c17",
      "size" : 2084765,
      "stats" : {
        "coreSize" : 102400,
        "downloadCount" : 6,
        "impressionCount" : 30,
        "issueCount" : 0,
        "starCount" : 1,
        "viewCount" : 3,
        "watcherCount" : 0
      },
      "subtitle" : "A whimsical game of excitement and delight",
      "tintColor" : "AF52DE",
      "version" : "0.9.138",
      "versionDate" : "2022-07-21T00:00:00Z",
      "versionDescription" : "**Full Changelog**: https://github.com/Cloud-Cuckoo/App/compare/0.9.137...0.9.138"
    },
    {
      "beta" : true,
      "bundleIdentifier" : "app.Crazy-Glue",
      "categories" : [

      ],
      "developerName" : "fairapps <fairapps@appfair.net>",
      "downloadURL" : "https://github.com/Crazy-Glue/App/releases/download/0.0.4/Crazy-Glue-macOS.zip",
      "fundingLinks" : [

      ],
      "iconURL" : "https://github.com/Crazy-Glue/App/releases/download/0.0.4/Crazy-Glue.png",
      "localizedDescription" : "Putting the pieces back together",
      "metadataURL" : "https://github.com/Crazy-Glue/App/releases/download/0.0.4/Info.plist#96efd2114846d6428e591a08296559254a988bab06ef4f2ec4518fe41dd2ed05",
      "name" : "Crazy Glue",
      "permissions" : [

      ],
      "readmeURL" : "https://github.com/Crazy-Glue/App/releases/download/0.0.4/README.md#5f665b7ecc017cdcd7917a881e68502b9062036dcc7caa1dddf81d644721debb",
      "screenshotURLs" : [
        "https://github.com/Crazy-Glue/App/releases/download/0.0.4/screenshot_01-mac-1936x1036.png"
      ],
      "sha256" : "bb88aca0dda7fed7a8fb7c8d0c292357e90d6326e1667f2dd8947f1b11f04eac",
      "size" : 2317729,
      "stats" : {
        "coreSize" : 68344,
        "downloadCount" : 14,
        "impressionCount" : 1675,
        "issueCount" : 0,
        "starCount" : 0,
        "viewCount" : 156,
        "watcherCount" : 0
      },
      "subtitle" : "Putting the pieces back together",
      "version" : "0.0.4",
      "versionDate" : "2022-01-23T00:00:00Z",
      "versionDescription" : "Release 0.0.4"
    },
    {
      "beta" : true,
      "bundleIdentifier" : "app.Down-Town",
      "categories" : [

      ],
      "developerName" : "fairapps <fairapps@appfair.net>",
      "downloadURL" : "https://github.com/Down-Town/App/releases/download/0.0.3/Down-Town-macOS.zip",
      "fundingLinks" : [

      ],
      "iconURL" : "https://github.com/Down-Town/App/releases/download/0.0.3/Down-Town.png",
      "localizedDescription" : "An urban street guide",
      "metadataURL" : "https://github.com/Down-Town/App/releases/download/0.0.3/Info.plist#96efd2114846d6428e591a08296559254a988bab06ef4f2ec4518fe41dd2ed05",
      "name" : "Down Town",
      "permissions" : [

      ],
      "readmeURL" : "https://github.com/Down-Town/App/releases/download/0.0.3/README.md#a5d47e741fb93553eeb4216a13174c5e3f5e5a04a19936ebb8fcba5f15f112f6",
      "screenshotURLs" : [
        "https://github.com/Down-Town/App/releases/download/0.0.3/screenshot_01-mac-dark-712x1078.png",
        "https://github.com/Down-Town/App/releases/download/0.0.3/screenshot_01-mac-light-712x1078.png"
      ],
      "sha256" : "100691a398de53e5ca21540f1dd272158c3c0307362bb61722aa536f24a4410d",
      "size" : 2338254,
      "stats" : {
        "coreSize" : 68344,
        "downloadCount" : 10,
        "impressionCount" : 1040,
        "issueCount" : 0,
        "starCount" : 0,
        "viewCount" : 82,
        "watcherCount" : 0
      },
      "subtitle" : "An urban street guide",
      "version" : "0.0.3",
      "versionDate" : "2022-01-25T00:00:00Z",
      "versionDescription" : "Release 0.0.3"
    },
    {
      "beta" : true,
      "bundleIdentifier" : "app.Encyclopedia-Galactica",
      "categories" : [

      ],
      "developerName" : "fairapps <fairapps@appfair.net>",
      "downloadURL" : "https://github.com/Encyclopedia-Galactica/App/releases/download/0.0.32/Encyclopedia-Galactica-macOS.zip",
      "fundingLinks" : [

      ],
      "iconURL" : "https://github.com/Encyclopedia-Galactica/App/releases/download/0.0.32/Encyclopedia-Galactica.png",
      "localizedDescription" : "All the accumulated knowledge in the galaxy",
      "metadataURL" : "https://github.com/Encyclopedia-Galactica/App/releases/download/0.0.32/Info.plist#96efd2114846d6428e591a08296559254a988bab06ef4f2ec4518fe41dd2ed05",
      "name" : "Encyclopedia Galactica",
      "permissions" : [
        {
          "type" : "network.client",
          "usageDescription" : "This app needs to access the network in order to download books"
        }
      ],
      "readmeURL" : "https://github.com/Encyclopedia-Galactica/App/releases/download/0.0.32/README.md#5f665b7ecc017cdcd7917a881e68502b9062036dcc7caa1dddf81d644721debb",
      "sha256" : "628b345aa3bf7e9cc0dc778d9369aabc96219ad24ba8bc4ffc262a133a0d484a",
      "size" : 2451488,
      "stats" : {
        "coreSize" : 68376,
        "downloadCount" : 5,
        "impressionCount" : 693,
        "issueCount" : 0,
        "starCount" : 0,
        "viewCount" : 51,
        "watcherCount" : 0
      },
      "subtitle" : "All the accumulated knowledge in the galaxy",
      "version" : "0.0.32",
      "versionDate" : "2022-01-24T00:00:00Z",
      "versionDescription" : "Release 0.0.32"
    },
    {
      "beta" : true,
      "bundleIdentifier" : "app.Eternal-September",
      "categories" : [

      ],
      "developerName" : "fairapps <fairapps@appfair.net>",
      "downloadURL" : "https://github.com/Eternal-September/App/releases/download/0.0.32/Eternal-September-macOS.zip",
      "fundingLinks" : [

      ],
      "iconURL" : "https://github.com/Eternal-September/App/releases/download/0.0.32/Eternal-September.png",
      "localizedDescription" : "An app for learning Roman Numerals",
      "metadataURL" : "https://github.com/Eternal-September/App/releases/download/0.0.32/Info.plist#5af4bf8fcdb5c153dd6d420a4ea10fd8664b88c04dc7d374db849f7d9ccd43ee",
      "name" : "Eternal September",
      "permissions" : [

      ],
      "readmeURL" : "https://github.com/Eternal-September/App/releases/download/0.0.32/README.md#721eb5f81ec8d74a19278cd6ff67d62ef22beecdc29657d3f3c65254f4b90a13",
      "sha256" : "4251fc77459c4621f0b52014fa2f76b8e73996bd07e5da04df4550649f586bb1",
      "size" : 2471831,
      "stats" : {
        "coreSize" : 152640,
        "downloadCount" : 4,
        "impressionCount" : 410,
        "issueCount" : 0,
        "starCount" : 0,
        "viewCount" : 40,
        "watcherCount" : 0
      },
      "subtitle" : "An app for learning Roman Numerals",
      "version" : "0.0.32",
      "versionDate" : "2022-01-26T00:00:00Z",
      "versionDescription" : "Release 0.0.32"
    },
    {
      "beta" : true,
      "bundleIdentifier" : "app.Festivus-Pole",
      "categories" : [

      ],
      "developerName" : "fairapps <fairapps@appfair.net>",
      "downloadURL" : "https://github.com/Festivus-Pole/App/releases/download/0.0.3/Festivus-Pole-macOS.zip",
      "fundingLinks" : [

      ],
      "iconURL" : "https://github.com/Festivus-Pole/App/releases/download/0.0.3/Festivus-Pole.png",
      "localizedDescription" : "A true Festivus celebration",
      "metadataURL" : "https://github.com/Festivus-Pole/App/releases/download/0.0.3/Info.plist#96efd2114846d6428e591a08296559254a988bab06ef4f2ec4518fe41dd2ed05",
      "name" : "Festivus Pole",
      "permissions" : [

      ],
      "readmeURL" : "https://github.com/Festivus-Pole/App/releases/download/0.0.3/README.md#5f665b7ecc017cdcd7917a881e68502b9062036dcc7caa1dddf81d644721debb",
      "screenshotURLs" : [
        "https://github.com/Festivus-Pole/App/releases/download/0.0.3/screenshot_01-mac-1936x1036.png"
      ],
      "sha256" : "4c85036bb30f16b52bb03b4781cd6c8c299a548ed568ee25eac226ef95829c4c",
      "size" : 2324945,
      "stats" : {
        "coreSize" : 68368,
        "downloadCount" : 7,
        "impressionCount" : 1066,
        "issueCount" : 0,
        "starCount" : 0,
        "viewCount" : 81,
        "watcherCount" : 0
      },
      "subtitle" : "A true Festivus celebration",
      "version" : "0.0.3",
      "versionDate" : "2022-01-23T00:00:00Z",
      "versionDescription" : "Release 0.0.3"
    },
    {
      "beta" : true,
      "bundleIdentifier" : "app.Fox-Glove",
      "categories" : [

      ],
      "developerName" : "fairapps <fairapps@appfair.net>",
      "downloadURL" : "https://github.com/Fox-Glove/App/releases/download/0.0.4/Fox-Glove-macOS.zip",
      "fundingLinks" : [

      ],
      "iconURL" : "https://github.com/Fox-Glove/App/releases/download/0.0.4/Fox-Glove.png",
      "localizedDescription" : "There, I fixed the web for you. You're welcome.",
      "metadataURL" : "https://github.com/Fox-Glove/App/releases/download/0.0.4/Info.plist#96efd2114846d6428e591a08296559254a988bab06ef4f2ec4518fe41dd2ed05",
      "name" : "Fox Glove",
      "permissions" : [

      ],
      "readmeURL" : "https://github.com/Fox-Glove/App/releases/download/0.0.4/README.md#5f665b7ecc017cdcd7917a881e68502b9062036dcc7caa1dddf81d644721debb",
      "screenshotURLs" : [
        "https://github.com/Fox-Glove/App/releases/download/0.0.4/screenshot_01-mac-dark-mac-1936x1036.png",
        "https://github.com/Fox-Glove/App/releases/download/0.0.4/screenshot_01-mac-light-mac-1936x1036.png"
      ],
      "sha256" : "b1c654805f85e21d51803ac45995486c60d4b7b9a8f5b4d648497f63fa5f42fa",
      "size" : 2427021,
      "stats" : {
        "coreSize" : 68344,
        "downloadCount" : 4,
        "impressionCount" : 1101,
        "issueCount" : 0,
        "starCount" : 0,
        "viewCount" : 80,
        "watcherCount" : 0
      },
      "subtitle" : "There, I fixed the web for you. You're welcome.",
      "version" : "0.0.4",
      "versionDate" : "2022-01-23T00:00:00Z",
      "versionDescription" : "Release 0.0.4"
    },
    {
      "beta" : true,
      "bundleIdentifier" : "app.Hear-Tell",
      "categories" : [

      ],
      "developerName" : "fairapps <fairapps@appfair.net>",
      "downloadURL" : "https://github.com/Hear-Tell/App/releases/download/0.3.38/Hear-Tell-macOS.zip",
      "fundingLinks" : [

      ],
      "iconURL" : "https://github.com/Hear-Tell/App/releases/download/0.3.38/Hear-Tell.png",
      "localizedDescription" : "Identify ambient sounds.",
      "metadataURL" : "https://github.com/Hear-Tell/App/releases/download/0.3.38/Info.plist#263a3737ed9d259afbaf4020b17e232339ca0bd4e981a0d8d160ba52476ec460",
      "name" : "Hear Tell",
      "permissions" : [
        {
          "type" : "device.microphone",
          "usageDescription" : "The microphone is used to process and identify ambient sounds."
        }
      ],
      "readmeURL" : "https://github.com/Hear-Tell/App/releases/download/0.3.38/README.md#5f665b7ecc017cdcd7917a881e68502b9062036dcc7caa1dddf81d644721debb",
      "sha256" : "637b46022cb1ac3b100471d8f7dff1cba01a1d552369f927e5eefa3ded6c93bc",
      "size" : 2309731,
      "stats" : {
        "coreSize" : 68344,
        "downloadCount" : 7,
        "impressionCount" : 694,
        "issueCount" : 0,
        "starCount" : 0,
        "viewCount" : 49,
        "watcherCount" : 0
      },
      "subtitle" : "Identify ambient sounds.",
      "version" : "0.3.38",
      "versionDate" : "2022-01-26T00:00:00Z",
      "versionDescription" : "Release 0.3.38"
    },
    {
      "beta" : false,
      "bundleIdentifier" : "app.Hex-Loupe",
      "categories" : [

      ],
      "developerName" : "fairapps <fairapps@appfair.org>",
      "downloadURL" : "https://github.com/Hex-Loupe/App/releases/download/0.0.20/Hex-Loupe-macOS.zip",
      "fundingLinks" : [

      ],
      "iconURL" : "https://github.com/Hex-Loupe/App/releases/download/0.0.20/Hex-Loupe.png",
      "localizedDescription" : "A hex viewer",
      "metadataURL" : "https://github.com/Hex-Loupe/App/releases/download/0.0.20/Info.plist#0fa563c571f2d2db3fd2b1f4530aae42417ae0dac3dd2a208e210c6f461ed692",
      "name" : "Hex Loupe",
      "permissions" : [
        {
          "type" : "com.apple.security.files.user-selected.read-only",
          "usageDescription" : "Hex examination requires the file read capability"
        }
      ],
      "readmeURL" : "https://github.com/Hex-Loupe/App/releases/download/0.0.20/README.md#600fdf6752d8c55b307fbad6d979e58285578294d41bea508d12d6f9f4efad92",
      "screenshotURLs" : [
        "https://github.com/Hex-Loupe/App/releases/download/0.0.20/screenshot_01-mac-dark-1820x1468.png",
        "https://github.com/Hex-Loupe/App/releases/download/0.0.20/screenshot_01-mac-light-1820x1468.png",
        "https://github.com/Hex-Loupe/App/releases/download/0.0.20/screenshot_02-mac-1864x1392.png",
        "https://github.com/Hex-Loupe/App/releases/download/0.0.20/screenshot_03-mac-2360x1742.png"
      ],
      "sha256" : "ed27a56682b188e537f44653c665d84dc3e4ce42ee73bbee723bfa946f624378",
      "size" : 2118382,
      "stats" : {
        "coreSize" : 102376,
        "downloadCount" : 20,
        "impressionCount" : 324,
        "issueCount" : 0,
        "starCount" : 0,
        "viewCount" : 17,
        "watcherCount" : 0
      },
      "subtitle" : "A hex viewer",
      "tintColor" : "A008FF",
      "version" : "0.0.20",
      "versionDate" : "2022-07-20T00:00:00Z",
      "versionDescription" : "**Full Changelog**: https://github.com/Hex-Loupe/App/compare/0.0.19...0.0.20"
    },
    {
      "beta" : true,
      "bundleIdentifier" : "app.Huffle-Puff",
      "categories" : [

      ],
      "developerName" : "fairapps <fairapps@appfair.net>",
      "downloadURL" : "https://github.com/Huffle-Puff/App/releases/download/0.0.7/Huffle-Puff-macOS.zip",
      "fundingLinks" : [

      ],
      "iconURL" : "https://github.com/Huffle-Puff/App/releases/download/0.0.7/Huffle-Puff.png",
      "localizedDescription" : "H.R. Huffle Puff ",
      "metadataURL" : "https://github.com/Huffle-Puff/App/releases/download/0.0.7/Info.plist#96efd2114846d6428e591a08296559254a988bab06ef4f2ec4518fe41dd2ed05",
      "name" : "Huffle Puff",
      "permissions" : [

      ],
      "readmeURL" : "https://github.com/Huffle-Puff/App/releases/download/0.0.7/README.md#5f665b7ecc017cdcd7917a881e68502b9062036dcc7caa1dddf81d644721debb",
      "sha256" : "de70cbd5d9af1cd40a5a4fe6cb761f3f8186ff97adc6c94be14325d7784fb23b",
      "size" : 2246786,
      "stats" : {
        "coreSize" : 152608,
        "downloadCount" : 4,
        "impressionCount" : 531,
        "issueCount" : 0,
        "starCount" : 0,
        "viewCount" : 45,
        "watcherCount" : 0
      },
      "subtitle" : "H.R. Huffle Puff ",
      "version" : "0.0.7",
      "versionDate" : "2022-01-24T00:00:00Z",
      "versionDescription" : "Release 0.0.7"
    },
    {
      "beta" : false,
      "bundleIdentifier" : "app.Lottie-Motion",
      "categories" : [

      ],
      "developerName" : "fairapps <fairapps@appfair.org>",
      "downloadURL" : "https://github.com/Lottie-Motion/App/releases/download/0.0.90/Lottie-Motion-macOS.zip",
      "fundingLinks" : [

      ],
      "iconURL" : "https://github.com/Lottie-Motion/App/releases/download/0.0.90/Lottie-Motion.png",
      "localizedDescription" : "Preview and experiment with Lottie animations",
      "metadataURL" : "https://github.com/Lottie-Motion/App/releases/download/0.0.90/Info.plist#44c670e69927d062463e3179bacd40a960984295fc24a5482381d6d00ccda5cc",
      "name" : "Lottie Motion",
      "permissions" : [
        {
          "type" : "com.apple.security.files.user-selected.read-write",
          "usageDescription" : "Load and save user-selected Lottie files."
        }
      ],
      "readmeURL" : "https://github.com/Lottie-Motion/App/releases/download/0.0.90/README.md#c0a4f63787b115e9ad0343a8293c7a7724f4a566891c78273babb85029fc0d26",
      "screenshotURLs" : [
        "https://github.com/Lottie-Motion/App/releases/download/0.0.90/screenshot_01-mac-1574x1294.png",
        "https://github.com/Lottie-Motion/App/releases/download/0.0.90/screenshot_02-mac-1228x916.png"
      ],
      "sha256" : "10f12c2de1d0a634050caec65eaf07aaf44642aa0310c88695022971b87451e7",
      "size" : 3926096,
      "stats" : {
        "coreSize" : 102576,
        "downloadCount" : 3,
        "impressionCount" : 325,
        "issueCount" : 0,
        "starCount" : 0,
        "viewCount" : 19,
        "watcherCount" : 0
      },
      "subtitle" : "Preview and experiment with Lottie animations",
      "version" : "0.0.90",
      "versionDate" : "2022-07-20T00:00:00Z",
      "versionDescription" : "**Full Changelog**: https://github.com/Lottie-Motion/App/compare/0.0.89...0.0.90"
    },
    {
      "beta" : false,
      "bundleIdentifier" : "app.Main-Course",
      "categories" : [

      ],
      "developerName" : "fairapps <fairapps@appfair.org>",
      "downloadURL" : "https://github.com/Main-Course/App/releases/download/0.0.16/Main-Course-macOS.zip",
      "fundingLinks" : [

      ],
      "iconURL" : "https://github.com/Main-Course/App/releases/download/0.0.16/Main-Course.png",
      "localizedDescription" : "An offline recipe book",
      "metadataURL" : "https://github.com/Main-Course/App/releases/download/0.0.16/Info.plist#27abe8e41c39d7eb3bb457c705e3816ee80253ee373e57f7a9c6704d85b542c8",
      "name" : "Main Course",
      "permissions" : [

      ],
      "readmeURL" : "https://github.com/Main-Course/App/releases/download/0.0.16/README.md#5194883aa60d146d8bb5b841bd0c6d1b7fbdc0f2d629fa05982519073beafec3",
      "screenshotURLs" : [
        "https://github.com/Main-Course/App/releases/download/0.0.16/screenshot_01-mac-dark-mac-984x842.png",
        "https://github.com/Main-Course/App/releases/download/0.0.16/screenshot_01-mac-light-mac-984x842.png"
      ],
      "sha256" : "926fde94d13f0a780767f29d4fce37592d73c03cf2b5b58fc4b9ae9c66e127aa",
      "size" : 12898573,
      "stats" : {
        "coreSize" : 102392,
        "downloadCount" : 2,
        "impressionCount" : 247,
        "issueCount" : 0,
        "starCount" : 0,
        "viewCount" : 16,
        "watcherCount" : 0
      },
      "subtitle" : "An offline recipe book",
      "version" : "0.0.16",
      "versionDate" : "2022-07-20T00:00:00Z",
      "versionDescription" : "**Full Changelog**: https://github.com/Main-Course/App/compare/0.0.15...0.0.16"
    },
    {
      "beta" : true,
      "bundleIdentifier" : "app.Media-Res",
      "categories" : [

      ],
      "developerName" : "fairapps <fairapps@appfair.net>",
      "downloadURL" : "https://github.com/Media-Res/App/releases/download/0.0.17/Media-Res-macOS.zip",
      "fundingLinks" : [

      ],
      "iconURL" : "https://github.com/Media-Res/App/releases/download/0.0.17/Media-Res.png",
      "localizedDescription" : "Art imitating Life (imitating Art)",
      "metadataURL" : "https://github.com/Media-Res/App/releases/download/0.0.17/Info.plist#96efd2114846d6428e591a08296559254a988bab06ef4f2ec4518fe41dd2ed05",
      "name" : "Media Res",
      "permissions" : [

      ],
      "readmeURL" : "https://github.com/Media-Res/App/releases/download/0.0.17/README.md#5f665b7ecc017cdcd7917a881e68502b9062036dcc7caa1dddf81d644721debb",
      "screenshotURLs" : [
        "https://github.com/Media-Res/App/releases/download/0.0.17/screenshot_01-mac-dark-mac-484x460.png",
        "https://github.com/Media-Res/App/releases/download/0.0.17/screenshot_01-mac-light-mac-484x460.png"
      ],
      "sha256" : "ec1eb7ae225c3031d06a93b032fbb4f5947a2eff6264446e3c3ebd452ac7faf0",
      "size" : 2356646,
      "stats" : {
        "coreSize" : 68344,
        "downloadCount" : 5,
        "impressionCount" : 958,
        "issueCount" : 0,
        "starCount" : 0,
        "viewCount" : 54,
        "watcherCount" : 0
      },
      "subtitle" : "Art imitating Life (imitating Art)",
      "version" : "0.0.17",
      "versionDate" : "2022-01-24T00:00:00Z",
      "versionDescription" : "Release 0.0.17"
    },
    {
      "beta" : true,
      "bundleIdentifier" : "app.Micro-Vector",
      "categories" : [

      ],
      "developerName" : "fairapps <fairapps@appfair.net>",
      "downloadURL" : "https://github.com/Micro-Vector/App/releases/download/0.0.8/Micro-Vector-macOS.zip",
      "fundingLinks" : [

      ],
      "iconURL" : "https://github.com/Micro-Vector/App/releases/download/0.0.8/Micro-Vector.png",
      "localizedDescription" : "A vector drawing app",
      "metadataURL" : "https://github.com/Micro-Vector/App/releases/download/0.0.8/Info.plist#96efd2114846d6428e591a08296559254a988bab06ef4f2ec4518fe41dd2ed05",
      "name" : "Micro Vector",
      "permissions" : [

      ],
      "readmeURL" : "https://github.com/Micro-Vector/App/releases/download/0.0.8/README.md#5f665b7ecc017cdcd7917a881e68502b9062036dcc7caa1dddf81d644721debb",
      "screenshotURLs" : [
        "https://github.com/Micro-Vector/App/releases/download/0.0.8/screenshot_01-mac-dark-1412x1082.png",
        "https://github.com/Micro-Vector/App/releases/download/0.0.8/screenshot_01-mac-light-1412x1082.png"
      ],
      "sha256" : "62d9c7a67c652dd3504c0574780869dcba80b5cae7617cb05790e0028d5fc482",
      "size" : 2791600,
      "stats" : {
        "coreSize" : 152624,
        "downloadCount" : 7,
        "impressionCount" : 599,
        "issueCount" : 0,
        "starCount" : 0,
        "viewCount" : 54,
        "watcherCount" : 0
      },
      "subtitle" : "A vector drawing app",
      "version" : "0.0.8",
      "versionDate" : "2022-01-24T00:00:00Z",
      "versionDescription" : "Release 0.0.8"
    },
    {
      "beta" : true,
      "bundleIdentifier" : "app.Name-Sense",
      "categories" : [

      ],
      "developerName" : "fairapps <fairapps@appfair.net>",
      "downloadURL" : "https://github.com/Name-Sense/App/releases/download/0.0.24/Name-Sense-macOS.zip",
      "fundingLinks" : [

      ],
      "iconURL" : "https://github.com/Name-Sense/App/releases/download/0.0.24/Name-Sense.png",
      "localizedDescription" : "A name picking app",
      "metadataURL" : "https://github.com/Name-Sense/App/releases/download/0.0.24/Info.plist#96efd2114846d6428e591a08296559254a988bab06ef4f2ec4518fe41dd2ed05",
      "name" : "Name Sense",
      "permissions" : [

      ],
      "readmeURL" : "https://github.com/Name-Sense/App/releases/download/0.0.24/README.md#5f665b7ecc017cdcd7917a881e68502b9062036dcc7caa1dddf81d644721debb",
      "screenshotURLs" : [
        "https://github.com/Name-Sense/App/releases/download/0.0.24/screenshot_01-mac-dark-1392x1126.png",
        "https://github.com/Name-Sense/App/releases/download/0.0.24/screenshot_01-mac-light-1392x1126.png"
      ],
      "sha256" : "44460c1912eb428c3c4a1d45791c1fe51d060489640854c73a420b07c4e1f6d8",
      "size" : 2650836,
      "stats" : {
        "coreSize" : 102472,
        "downloadCount" : 4,
        "impressionCount" : 817,
        "issueCount" : 0,
        "starCount" : 0,
        "viewCount" : 48,
        "watcherCount" : 0
      },
      "subtitle" : "A name picking app",
      "version" : "0.0.24",
      "versionDate" : "2022-02-12T00:00:00Z",
      "versionDescription" : "Release 0.0.24"
    },
    {
      "beta" : false,
      "bundleIdentifier" : "app.Net-Skip",
      "categories" : [

      ],
      "developerName" : "fairapps <fairapps@appfair.org>",
      "downloadURL" : "https://github.com/Net-Skip/App/releases/download/0.0.42/Net-Skip-macOS.zip",
      "fundingLinks" : [

      ],
      "iconURL" : "https://github.com/Net-Skip/App/releases/download/0.0.42/Net-Skip.png",
      "localizedDescription" : "Web browsing for the connoisseur",
      "metadataURL" : "https://github.com/Net-Skip/App/releases/download/0.0.42/Info.plist#a33450cc7f2a005d158dbb93a34a63fb6ba757879198704aa44d642056468194",
      "name" : "Net Skip",
      "permissions" : [
        {
          "type" : "network.client",
          "usageDescription" : "This app needs to access the network to load web pages."
        },
        {
          "type" : "files.user-selected.read-write",
          "usageDescription" : "This app needs to write files in order to save downloads."
        }
      ],
      "readmeURL" : "https://github.com/Net-Skip/App/releases/download/0.0.42/README.md#d326ba451e5c04096133372568119e6504700b011674410c1255233adf5a72fd",
      "screenshotURLs" : [
        "https://github.com/Net-Skip/App/releases/download/0.0.42/screenshot_01-mac-dark-2528x2010.png",
        "https://github.com/Net-Skip/App/releases/download/0.0.42/screenshot_01-mac-light-2528x2010.png",
        "https://github.com/Net-Skip/App/releases/download/0.0.42/screenshot_02-mac-dark-2528x2010.png",
        "https://github.com/Net-Skip/App/releases/download/0.0.42/screenshot_02-mac-light-2528x2010.png",
        "https://github.com/Net-Skip/App/releases/download/0.0.42/screenshot_03-mac-dark-2528x2010.png",
        "https://github.com/Net-Skip/App/releases/download/0.0.42/screenshot_03-mac-light-2528x2010.png"
      ],
      "sha256" : "93b676dee4a4c71809dfe57966f38ac739902432bc5ab501cd87e36bb45e2ed6",
      "size" : 3687703,
      "stats" : {
        "coreSize" : 102472,
        "downloadCount" : 16,
        "impressionCount" : 2726,
        "issueCount" : 0,
        "starCount" : 0,
        "viewCount" : 450,
        "watcherCount" : 0
      },
      "subtitle" : "Web browsing for the connoisseur",
      "version" : "0.0.42",
      "versionDate" : "2022-05-26T00:00:00Z",
      "versionDescription" : "**Full Changelog**: https://github.com/Net-Skip/App/compare/0.0.41...0.0.42"
    },
    {
      "beta" : true,
      "bundleIdentifier" : "app.Neural-Scry",
      "categories" : [

      ],
      "developerName" : "fairapps <fairapps@appfair.net>",
      "downloadURL" : "https://github.com/Neural-Scry/App/releases/download/0.0.51/Neural-Scry-macOS.zip",
      "fundingLinks" : [

      ],
      "iconURL" : "https://github.com/Neural-Scry/App/releases/download/0.0.51/Neural-Scry.png",
      "localizedDescription" : "Brain scanner",
      "metadataURL" : "https://github.com/Neural-Scry/App/releases/download/0.0.51/Info.plist#2215eff2478180960a9c3d722d16eb05a760a8a09dab75af2881197aaff61bd1",
      "name" : "Neural Scry",
      "permissions" : [
        {
          "type" : "network.client",
          "usageDescription" : "This enabled this permission for testing"
        },
        {
          "type" : "network.server",
          "usageDescription" : "This enabled this permission for testing"
        },
        {
          "type" : "device.camera",
          "usageDescription" : "This enabled this permission for testing"
        },
        {
          "type" : "device.microphone",
          "usageDescription" : "This enabled this permission for testing"
        },
        {
          "type" : "device.usb",
          "usageDescription" : "This enabled this permission for testing"
        },
        {
          "type" : "cs.debugger",
          "usageDescription" : "This enabled this permission for testing"
        },
        {
          "type" : "temporary-exception.mach-lookup.global-name",
          "usageDescription" : "This enabled this permission for testing"
        }
      ],
      "readmeURL" : "https://github.com/Neural-Scry/App/releases/download/0.0.51/README.md#f9af449c34702872740ca1db657be31a62c8caa3f1dc77e96d64a0fb040ef186",
      "sha256" : "b88e1400b49f2a9949e4acd5564bbb41415b3d244a309eee5f73ecbf20ff09ab",
      "size" : 2306403,
      "stats" : {
        "coreSize" : 153232,
        "downloadCount" : 4,
        "impressionCount" : 137,
        "issueCount" : 0,
        "starCount" : 0,
        "viewCount" : 19,
        "watcherCount" : 0
      },
      "subtitle" : "Brain scanner",
      "version" : "0.0.51",
      "versionDate" : "2022-01-16T00:00:00Z",
      "versionDescription" : "Release 0.0.51"
    },
    {
      "beta" : false,
      "bundleIdentifier" : "app.Next-Edit",
      "categories" : [

      ],
      "developerName" : "fairapps <fairapps@appfair.net>",
      "downloadURL" : "https://github.com/Next-Edit/App/releases/download/0.4.18/Next-Edit-macOS.zip",
      "fundingLinks" : [

      ],
      "iconURL" : "https://github.com/Next-Edit/App/releases/download/0.4.18/Next-Edit.png",
      "localizedDescription" : "Syntactic Text Editor",
      "metadataURL" : "https://github.com/Next-Edit/App/releases/download/0.4.18/Info.plist#78288b2b9832e3d0ebf68ffe39ee3f69a2a7a5253a221658250d131eda738dc8",
      "name" : "Next Edit",
      "permissions" : [
        {
          "type" : "files.user-selected.read-write",
          "usageDescription" : "This app needs to read and write files in order to edit text."
        }
      ],
      "readmeURL" : "https://github.com/Next-Edit/App/releases/download/0.4.18/README.md#f9cf464cfc7a08451b3af964a530a17e448301cb21bdf6477856ee9080340e07",
      "screenshotURLs" : [
        "https://github.com/Next-Edit/App/releases/download/0.4.18/screenshot_01-mac-2006x1520.png"
      ],
      "sha256" : "6ee478349595968078112b52bbde2bf14753271fd31531bea7c0bca10977d28a",
      "size" : 6702858,
      "stats" : {
        "coreSize" : 152800,
        "downloadCount" : 21,
        "impressionCount" : 2390,
        "issueCount" : 0,
        "starCount" : 0,
        "viewCount" : 440,
        "watcherCount" : 0
      },
      "subtitle" : "Syntactic Text Editor",
      "version" : "0.4.18",
      "versionDate" : "2022-01-20T00:00:00Z",
      "versionDescription" : "Release 0.4.18"
    },
    {
      "beta" : true,
      "bundleIdentifier" : "app.Pan-Opticon",
      "categories" : [

      ],
      "developerName" : "fairapps <fairapps@appfair.net>",
      "downloadURL" : "https://github.com/Pan-Opticon/App/releases/download/0.2.22/Pan-Opticon-macOS.zip",
      "fundingLinks" : [

      ],
      "iconURL" : "https://github.com/Pan-Opticon/App/releases/download/0.2.22/Pan-Opticon.png",
      "localizedDescription" : "Watch the Watchers",
      "metadataURL" : "https://github.com/Pan-Opticon/App/releases/download/0.2.22/Info.plist#96efd2114846d6428e591a08296559254a988bab06ef4f2ec4518fe41dd2ed05",
      "name" : "Pan Opticon",
      "permissions" : [

      ],
      "readmeURL" : "https://github.com/Pan-Opticon/App/releases/download/0.2.22/README.md#5f665b7ecc017cdcd7917a881e68502b9062036dcc7caa1dddf81d644721debb",
      "screenshotURLs" : [
        "https://github.com/Pan-Opticon/App/releases/download/0.2.22/screenshot_01-mac-dark-mac-1220x1050.png",
        "https://github.com/Pan-Opticon/App/releases/download/0.2.22/screenshot_01-mac-light-mac-1220x1050.png"
      ],
      "sha256" : "6f6765b12411f568825a8def3d0187ca12f2d3d1f9ce62edc8dc6d8c4151fce8",
      "size" : 2617474,
      "stats" : {
        "coreSize" : 68360,
        "downloadCount" : 4,
        "impressionCount" : 361,
        "issueCount" : 0,
        "starCount" : 0,
        "viewCount" : 41,
        "watcherCount" : 0
      },
      "subtitle" : "Watch the Watchers",
      "tintColor" : "CC00AA",
      "version" : "0.2.22",
      "versionDate" : "2022-01-24T00:00:00Z",
      "versionDescription" : "Release 0.2.22"
    },
    {
      "beta" : true,
      "bundleIdentifier" : "app.Red-Light-Green-Light",
      "categories" : [

      ],
      "developerName" : "fairapps <fairapps@appfair.net>",
      "downloadURL" : "https://github.com/Red-Light-Green-Light/App/releases/download/0.0.12/Red-Light-Green-Light-macOS.zip",
      "fundingLinks" : [

      ],
      "iconURL" : "https://github.com/Red-Light-Green-Light/App/releases/download/0.0.12/Red-Light-Green-Light.png",
      "localizedDescription" : "무궁화 꽃이 피었습니다",
      "metadataURL" : "https://github.com/Red-Light-Green-Light/App/releases/download/0.0.12/Info.plist#96efd2114846d6428e591a08296559254a988bab06ef4f2ec4518fe41dd2ed05",
      "name" : "Red Light Green Light",
      "permissions" : [

      ],
      "readmeURL" : "https://github.com/Red-Light-Green-Light/App/releases/download/0.0.12/README.md#5f665b7ecc017cdcd7917a881e68502b9062036dcc7caa1dddf81d644721debb",
      "screenshotURLs" : [
        "https://github.com/Red-Light-Green-Light/App/releases/download/0.0.12/screenshot_01-mac-dark-2024x1124.png",
        "https://github.com/Red-Light-Green-Light/App/releases/download/0.0.12/screenshot_01-mac-light-2024x1124.png"
      ],
      "sha256" : "9074f553a7b0f8817aa76aa7cd302bb62af52c9fbca7ced06805ddfeab0526d6",
      "size" : 2448634,
      "stats" : {
        "coreSize" : 152640,
        "downloadCount" : 4,
        "impressionCount" : 748,
        "issueCount" : 0,
        "starCount" : 0,
        "viewCount" : 50,
        "watcherCount" : 0
      },
      "subtitle" : "무궁화 꽃이 피었습니다",
      "version" : "0.0.12",
      "versionDate" : "2022-02-02T00:00:00Z",
      "versionDescription" : "Release 0.0.12"
    },
    {
      "beta" : true,
      "bundleIdentifier" : "app.SQL-Hero",
      "categories" : [

      ],
      "developerName" : "fairapps <fairapps@appfair.net>",
      "downloadURL" : "https://github.com/SQL-Hero/App/releases/download/0.0.8/SQL-Hero-macOS.zip",
      "fundingLinks" : [

      ],
      "iconURL" : "https://github.com/SQL-Hero/App/releases/download/0.0.8/SQL-Hero.png",
      "localizedDescription" : "Query Like a Boss",
      "metadataURL" : "https://github.com/SQL-Hero/App/releases/download/0.0.8/Info.plist#f4f5af5e949181c450648183357dc49105d946769ffbc87050c930326d2ff8c5",
      "name" : "SQL Hero",
      "permissions" : [
        {
          "type" : "network.client",
          "usageDescription" : "Network client access required to connect to remote databases."
        },
        {
          "type" : "network.server",
          "usageDescription" : "Network server access is needed to handle requests."
        },
        {
          "type" : "files.user-selected.read-write",
          "usageDescription" : "Filesystem access required to read and write local databases."
        }
      ],
      "readmeURL" : "https://github.com/SQL-Hero/App/releases/download/0.0.8/README.md#5f665b7ecc017cdcd7917a881e68502b9062036dcc7caa1dddf81d644721debb",
      "screenshotURLs" : [
        "https://github.com/SQL-Hero/App/releases/download/0.0.8/screenshot_01-mac-dark-1264x1058.png",
        "https://github.com/SQL-Hero/App/releases/download/0.0.8/screenshot_01-mac-light-1264x1058.png"
      ],
      "sha256" : "7b7acaf8df44e8d45ff3cd38b9b0273cbe4147d00ded68d55e2608ccc8b2068a",
      "size" : 8727214,
      "stats" : {
        "coreSize" : 152704,
        "downloadCount" : 8,
        "impressionCount" : 331,
        "issueCount" : 0,
        "starCount" : 0,
        "viewCount" : 33,
        "watcherCount" : 0
      },
      "subtitle" : "Query Like a Boss",
      "version" : "0.0.8",
      "versionDate" : "2022-01-24T00:00:00Z",
      "versionDescription" : "Release 0.0.8"
    },
    {
      "beta" : true,
      "bundleIdentifier" : "app.Silly-Little-App",
      "categories" : [

      ],
      "developerName" : "fair-ground action <fair-ground@users.noreply.github.com>",
      "downloadURL" : "https://github.com/Silly-Little-App/App/releases/download/0.0.1/Silly-Little-App-macOS.zip",
      "fundingLinks" : [

      ],
      "iconURL" : "https://github.com/Silly-Little-App/App/releases/download/0.0.1/Silly-Little-App.png",
      "localizedDescription" : "A simple little app to demonstrate the App Fair",
      "metadataURL" : "https://github.com/Silly-Little-App/App/releases/download/0.0.1/Info.plist#27abe8e41c39d7eb3bb457c705e3816ee80253ee373e57f7a9c6704d85b542c8",
      "name" : "Silly Little App",
      "permissions" : [

      ],
      "readmeURL" : "https://github.com/Silly-Little-App/App/releases/download/0.0.1/README.md#e72aab68c394821d6a058ec5fb365b734d06301321a1b882ef9d27411fcdcec9",
      "sha256" : "91e9f817b8f49ba57115b3abe7e327e295f15f4b2b28c3c0f188fc64d1e6f819",
      "size" : 1971250,
      "stats" : {
        "coreSize" : 170144,
        "downloadCount" : 5,
        "impressionCount" : 631,
        "issueCount" : 0,
        "starCount" : 0,
        "viewCount" : 85,
        "watcherCount" : 0
      },
      "subtitle" : "A simple little app to demonstrate the App Fair",
      "version" : "0.0.1",
      "versionDate" : "2022-07-04T00:00:00Z",
      "versionDescription" : ""
    },
    {
      "beta" : true,
      "bundleIdentifier" : "app.Sita-Sings-the-Blues",
      "categories" : [

      ],
      "developerName" : "fairapps <fairapps@appfair.org>",
      "downloadURL" : "https://github.com/Sita-Sings-the-Blues/App/releases/download/0.0.49/Sita-Sings-the-Blues-macOS.zip",
      "fundingLinks" : [

      ],
      "iconURL" : "https://github.com/Sita-Sings-the-Blues/App/releases/download/0.0.49/Sita-Sings-the-Blues.png",
      "localizedDescription" : "The movie \"Sita Sings the Blues\"",
      "metadataURL" : "https://github.com/Sita-Sings-the-Blues/App/releases/download/0.0.49/Info.plist#27abe8e41c39d7eb3bb457c705e3816ee80253ee373e57f7a9c6704d85b542c8",
      "name" : "Sita Sings the Blues",
      "permissions" : [

      ],
      "readmeURL" : "https://github.com/Sita-Sings-the-Blues/App/releases/download/0.0.49/README.md#60a2f8449bb3f6503232c4b9f88301ec77109750a69193125924af6211fb384e",
      "screenshotURLs" : [
        "https://github.com/Sita-Sings-the-Blues/App/releases/download/0.0.49/screenshot_01-mac-2540x1658.png",
        "https://github.com/Sita-Sings-the-Blues/App/releases/download/0.0.49/screenshot_02-mac-2540x1658.png",
        "https://github.com/Sita-Sings-the-Blues/App/releases/download/0.0.49/screenshot_03-mac-2540x1658.png"
      ],
      "sha256" : "4f1c7a3e65440f41b2e9a8f8b4d5774dcf52e4566f35bdce470fca0c63199247",
      "size" : 1454736702,
      "stats" : {
        "coreSize" : 102952,
        "downloadCount" : 5,
        "impressionCount" : 347,
        "issueCount" : 0,
        "starCount" : 0,
        "viewCount" : 50,
        "watcherCount" : 0
      },
      "subtitle" : "The movie \"Sita Sings the Blues\"",
      "version" : "0.0.49",
      "versionDate" : "2022-04-08T00:00:00Z",
      "versionDescription" : "Release 0.0.49"
    },
    {
      "beta" : false,
      "bundleIdentifier" : "app.Stanza-Redux",
      "categories" : [

      ],
      "developerName" : "fairapps <fairapps@appfair.org>",
      "downloadURL" : "https://github.com/Stanza-Redux/App/releases/download/0.3.38/Stanza-Redux-macOS.zip",
      "fundingLinks" : [

      ],
      "iconURL" : "https://github.com/Stanza-Redux/App/releases/download/0.3.38/Stanza-Redux.png",
      "localizedDescription" : "An electronic book reader",
      "metadataURL" : "https://github.com/Stanza-Redux/App/releases/download/0.3.38/Info.plist#b74fe2ab3fbba805f94a9fc4bac7c1fe82a59251d8330f281689fa77368ec297",
      "name" : "Stanza Redux",
      "permissions" : [
        {
          "type" : "com.apple.security.network.client",
          "usageDescription" : "This app needs to access the network in order to access books"
        },
        {
          "type" : "com.apple.security.files.user-selected.read-only",
          "usageDescription" : "This app needs to read ebook files"
        }
      ],
      "readmeURL" : "https://github.com/Stanza-Redux/App/releases/download/0.3.38/README.md#d470949a6400c6fbd898adbfe40b6a3e022bd22341dd1eb5ffed1f98f57030e1",
      "screenshotURLs" : [
        "https://github.com/Stanza-Redux/App/releases/download/0.3.38/screenshot_01-mac-dark-2436x2012.png",
        "https://github.com/Stanza-Redux/App/releases/download/0.3.38/screenshot_01-mac-light-2436x2012.png"
      ],
      "sha256" : "6fa8fef752062dfc50d41f3271307bd3dee6d387cdc978b901facfe8db7ab891",
      "size" : 3810588,
      "stats" : {
        "coreSize" : 102480,
        "downloadCount" : 1,
        "impressionCount" : 226,
        "issueCount" : 0,
        "starCount" : 1,
        "viewCount" : 17,
        "watcherCount" : 0
      },
      "subtitle" : "An electronic book reader",
      "tintColor" : "00375C",
      "version" : "0.3.38",
      "versionDate" : "2022-07-20T00:00:00Z",
      "versionDescription" : "**Full Changelog**: https://github.com/Stanza-Redux/App/compare/0.3.37...0.3.38"
    },
    {
      "beta" : true,
      "bundleIdentifier" : "app.Story-Points",
      "categories" : [

      ],
      "developerName" : "fairapps <fairapps@appfair.net>",
      "downloadURL" : "https://github.com/Story-Points/App/releases/download/0.0.6/Story-Points-macOS.zip",
      "fundingLinks" : [

      ],
      "iconURL" : "https://github.com/Story-Points/App/releases/download/0.0.6/Story-Points.png",
      "localizedDescription" : "UX Design Tool",
      "metadataURL" : "https://github.com/Story-Points/App/releases/download/0.0.6/Info.plist#96efd2114846d6428e591a08296559254a988bab06ef4f2ec4518fe41dd2ed05",
      "name" : "Story Points",
      "permissions" : [

      ],
      "readmeURL" : "https://github.com/Story-Points/App/releases/download/0.0.6/README.md#5f665b7ecc017cdcd7917a881e68502b9062036dcc7caa1dddf81d644721debb",
      "screenshotURLs" : [
        "https://github.com/Story-Points/App/releases/download/0.0.6/screenshot_01-mac-light-mac-2024x1124.png",
        "https://github.com/Story-Points/App/releases/download/0.0.6/screenshot_01-mac-dark-mac-2024x1124.png"
      ],
      "sha256" : "e6b3bff7dd943fea8dfab2ee57d61a454bd8c4ddb2f443ed649cd93729352f8c",
      "size" : 2383127,
      "stats" : {
        "coreSize" : 152624,
        "downloadCount" : 8,
        "impressionCount" : 379,
        "issueCount" : 0,
        "starCount" : 0,
        "viewCount" : 57,
        "watcherCount" : 0
      },
      "subtitle" : "UX Design Tool",
      "version" : "0.0.6",
      "versionDate" : "2022-01-24T00:00:00Z",
      "versionDescription" : "Release 0.0.6"
    },
    {
      "beta" : true,
      "bundleIdentifier" : "app.Tidal-Zone",
      "categories" : [

      ],
      "developerName" : "fairapps <fairapps@appfair.net>",
      "downloadURL" : "https://github.com/Tidal-Zone/App/releases/download/0.0.20/Tidal-Zone-macOS.zip",
      "fundingLinks" : [

      ],
      "iconURL" : "https://github.com/Tidal-Zone/App/releases/download/0.0.20/Tidal-Zone.png",
      "localizedDescription" : "What tide is it right now?",
      "metadataURL" : "https://github.com/Tidal-Zone/App/releases/download/0.0.20/Info.plist#26ac8b5021fc68a699acaae189251fb8f2e42f419764130e697d3669e95cada7",
      "name" : "Tidal Zone",
      "permissions" : [

      ],
      "readmeURL" : "https://github.com/Tidal-Zone/App/releases/download/0.0.20/README.md#81f629784b7c2a4c640fd99452df327d7f1d7363b39db3c37f65f108ddd28c8f",
      "screenshotURLs" : [
        "https://github.com/Tidal-Zone/App/releases/download/0.0.20/screenshot-mac-01-2024x1124.png"
      ],
      "sha256" : "db951840a4f86b2e0589cb1b41b2c8695570af19f0af03dafb5d79af5fa2734f",
      "size" : 2539951,
      "stats" : {
        "coreSize" : 102472,
        "downloadCount" : 7,
        "impressionCount" : 1004,
        "issueCount" : 0,
        "starCount" : 0,
        "viewCount" : 57,
        "watcherCount" : 0
      },
      "subtitle" : "What tide is it right now?",
      "version" : "0.0.20",
      "versionDate" : "2022-02-12T00:00:00Z",
      "versionDescription" : "Release 0.0.20"
    },
    {
      "beta" : true,
      "bundleIdentifier" : "app.Trivial-Quiz",
      "categories" : [

      ],
      "developerName" : "fairapps <fairapps@appfair.net>",
      "downloadURL" : "https://github.com/Trivial-Quiz/App/releases/download/0.0.16/Trivial-Quiz-macOS.zip",
      "fundingLinks" : [

      ],
      "iconURL" : "https://github.com/Trivial-Quiz/App/releases/download/0.0.16/Trivial-Quiz.png",
      "localizedDescription" : "A little quiz game",
      "metadataURL" : "https://github.com/Trivial-Quiz/App/releases/download/0.0.16/Info.plist#96efd2114846d6428e591a08296559254a988bab06ef4f2ec4518fe41dd2ed05",
      "name" : "Trivial Quiz",
      "permissions" : [

      ],
      "readmeURL" : "https://github.com/Trivial-Quiz/App/releases/download/0.0.16/README.md#5f665b7ecc017cdcd7917a881e68502b9062036dcc7caa1dddf81d644721debb",
      "screenshotURLs" : [
        "https://github.com/Trivial-Quiz/App/releases/download/0.0.16/screenshot_01-mac-dark-mac-2024x1124.png",
        "https://github.com/Trivial-Quiz/App/releases/download/0.0.16/screenshot_01-mac-light-mac-2024x1124.png"
      ],
      "sha256" : "8eb419e580e42211fd47a3e67e62f2b6a80f0e191695a3891451e49530d203f4",
      "size" : 2472954,
      "stats" : {
        "coreSize" : 102480,
        "downloadCount" : 1,
        "impressionCount" : 463,
        "issueCount" : 0,
        "starCount" : 0,
        "viewCount" : 36,
        "watcherCount" : 0
      },
      "subtitle" : "A little quiz game",
      "version" : "0.0.16",
      "versionDate" : "2022-02-12T00:00:00Z",
      "versionDescription" : "Release 0.0.16"
    },
    {
      "beta" : false,
      "bundleIdentifier" : "app.Tune-Out",
      "categories" : [

      ],
      "developerName" : "fairapps <fairapps@appfair.org>",
      "downloadURL" : "https://github.com/Tune-Out/App/releases/download/0.8.446/Tune-Out-macOS.zip",
      "fundingLinks" : [

      ],
      "iconURL" : "https://github.com/Tune-Out/App/releases/download/0.8.446/Tune-Out.png",
      "localizedDescription" : "Stream Internet Radio",
      "metadataURL" : "https://github.com/Tune-Out/App/releases/download/0.8.446/Info.plist#ec57c2f0b0592e58a706d3f7dae4f3b6c3c56500286c25446cf9fe7b614a6552",
      "name" : "Tune Out",
      "permissions" : [
        {
          "type" : "com.apple.security.network.client",
          "usageDescription" : "This app needs to access the network in order to stream internet radio stations."
        }
      ],
      "readmeURL" : "https://github.com/Tune-Out/App/releases/download/0.8.446/README.md#f9af650543d6a02cb7650a7753b9ffaf251c99c7f80d0fd2e7ee5e4ff5c74130",
      "screenshotURLs" : [
        "https://github.com/Tune-Out/App/releases/download/0.8.446/screenshot_01-mac-2212x1462.png",
        "https://github.com/Tune-Out/App/releases/download/0.8.446/screenshot_01-mac-dark-2250x1632.png",
        "https://github.com/Tune-Out/App/releases/download/0.8.446/screenshot_01-mac-light-2250x1632.png",
        "https://github.com/Tune-Out/App/releases/download/0.8.446/screenshot_01-mac-light-2582x1498.png",
        "https://github.com/Tune-Out/App/releases/download/0.8.446/screenshot_02-mac-2534x1112.png",
        "https://github.com/Tune-Out/App/releases/download/0.8.446/screenshot_03-mac-2180x1464.png"
      ],
      "sha256" : "027dd57a3e1c83191e52c0ca3ba7f71c76cf68eed87b7d7315c097a181411bae",
      "size" : 9431905,
      "stats" : {
        "coreSize" : 103112,
        "downloadCount" : 4,
        "impressionCount" : 286,
        "issueCount" : 0,
        "starCount" : 1,
        "viewCount" : 28,
        "watcherCount" : 0
      },
      "subtitle" : "Stream Internet Radio",
      "tintColor" : "32ADE6",
      "version" : "0.8.446",
      "versionDate" : "2022-07-20T00:00:00Z",
      "versionDescription" : "**Full Changelog**: https://github.com/Tune-Out/App/compare/0.8.445...0.8.446"
    },
    {
      "beta" : true,
      "bundleIdentifier" : "app.Tweet-Storm",
      "categories" : [

      ],
      "developerName" : "fairapps <fairapps@appfair.org>",
      "downloadURL" : "https://github.com/Tweet-Storm/App/releases/download/0.0.12/Tweet-Storm-macOS.zip",
      "fundingLinks" : [

      ],
      "iconURL" : "https://github.com/Tweet-Storm/App/releases/download/0.0.12/Tweet-Storm.png",
      "localizedDescription" : "Unleash your inner dialog",
      "metadataURL" : "https://github.com/Tweet-Storm/App/releases/download/0.0.12/Info.plist#27abe8e41c39d7eb3bb457c705e3816ee80253ee373e57f7a9c6704d85b542c8",
      "name" : "Tweet Storm",
      "permissions" : [

      ],
      "readmeURL" : "https://github.com/Tweet-Storm/App/releases/download/0.0.12/README.md#5f665b7ecc017cdcd7917a881e68502b9062036dcc7caa1dddf81d644721debb",
      "sha256" : "98dbae297fcc754e3695a96c65a3e18b91e887353e7348ed2287914740c56564",
      "size" : 2624128,
      "stats" : {
        "coreSize" : 102392,
        "downloadCount" : 2,
        "impressionCount" : 322,
        "issueCount" : 0,
        "starCount" : 0,
        "viewCount" : 22,
        "watcherCount" : 0
      },
      "subtitle" : "Unleash your inner dialog",
      "version" : "0.0.12",
      "versionDate" : "2022-05-01T00:00:00Z",
      "versionDescription" : "Release 0.0.12"
    },
    {
      "beta" : true,
      "bundleIdentifier" : "app.Ultra-Light",
      "categories" : [

      ],
      "developerName" : "fairapps <fairapps@appfair.net>",
      "downloadURL" : "https://github.com/Ultra-Light/App/releases/download/0.0.7/Ultra-Light-macOS.zip",
      "fundingLinks" : [

      ],
      "iconURL" : "https://github.com/Ultra-Light/App/releases/download/0.0.7/Ultra-Light.png",
      "localizedDescription" : "A bit of lite reading",
      "metadataURL" : "https://github.com/Ultra-Light/App/releases/download/0.0.7/Info.plist#96efd2114846d6428e591a08296559254a988bab06ef4f2ec4518fe41dd2ed05",
      "name" : "Ultra Light",
      "permissions" : [

      ],
      "readmeURL" : "https://github.com/Ultra-Light/App/releases/download/0.0.7/README.md#5f665b7ecc017cdcd7917a881e68502b9062036dcc7caa1dddf81d644721debb",
      "screenshotURLs" : [
        "https://github.com/Ultra-Light/App/releases/download/0.0.7/screenshot_01-mac-dark-mac-1938x482.png",
        "https://github.com/Ultra-Light/App/releases/download/0.0.7/screenshot_02-mac-dark-mac-478x1226.png",
        "https://github.com/Ultra-Light/App/releases/download/0.0.7/screenshot_01-mac-light-mac-1938x482.png",
        "https://github.com/Ultra-Light/App/releases/download/0.0.7/screenshot_02-mac-light-mac-478x1226.png"
      ],
      "sha256" : "633d678f1dcf6a960ecab0ecff581f2ceb6c1e191e2b7bfea5ba67b4173cdcb1",
      "size" : 2271510,
      "stats" : {
        "coreSize" : 68360,
        "downloadCount" : 4,
        "impressionCount" : 394,
        "issueCount" : 0,
        "starCount" : 0,
        "viewCount" : 44,
        "watcherCount" : 0
      },
      "subtitle" : "A bit of lite reading",
      "version" : "0.0.7",
      "versionDate" : "2022-01-21T00:00:00Z",
      "versionDescription" : "Release 0.0.7"
    },
    {
      "beta" : true,
      "bundleIdentifier" : "app.Unclear-Purpose",
      "categories" : [

      ],
      "developerName" : "fairapps <fairapps@appfair.net>",
      "downloadURL" : "https://github.com/Unclear-Purpose/App/releases/download/0.0.5/Unclear-Purpose-macOS.zip",
      "fundingLinks" : [

      ],
      "iconURL" : "https://github.com/Unclear-Purpose/App/releases/download/0.0.5/Unclear-Purpose.png",
      "localizedDescription" : "An unclear app",
      "metadataURL" : "https://github.com/Unclear-Purpose/App/releases/download/0.0.5/Info.plist#96efd2114846d6428e591a08296559254a988bab06ef4f2ec4518fe41dd2ed05",
      "name" : "Unclear Purpose",
      "permissions" : [

      ],
      "readmeURL" : "https://github.com/Unclear-Purpose/App/releases/download/0.0.5/README.md#5f665b7ecc017cdcd7917a881e68502b9062036dcc7caa1dddf81d644721debb",
      "sha256" : "7e52be3c6558eddf0eab2c32d5069a48036241fc6e118570a6b2a0654fcd8a79",
      "size" : 2323720,
      "stats" : {
        "coreSize" : 68368,
        "downloadCount" : 3,
        "impressionCount" : 360,
        "issueCount" : 0,
        "starCount" : 0,
        "viewCount" : 28,
        "watcherCount" : 0
      },
      "subtitle" : "An unclear app",
      "version" : "0.0.5",
      "versionDate" : "2022-01-25T00:00:00Z",
      "versionDescription" : "Release 0.0.5"
    },
    {
      "beta" : true,
      "bundleIdentifier" : "app.Visi-Calc",
      "categories" : [

      ],
      "developerName" : "fairapps <fairapps@appfair.net>",
      "downloadURL" : "https://github.com/Visi-Calc/App/releases/download/0.0.37/Visi-Calc-macOS.zip",
      "fundingLinks" : [

      ],
      "iconURL" : "https://github.com/Visi-Calc/App/releases/download/0.0.37/Visi-Calc.png",
      "localizedDescription" : "A business app for business-folk",
      "metadataURL" : "https://github.com/Visi-Calc/App/releases/download/0.0.37/Info.plist#d1d3028fa679289adb1356dbcf36b05a7b11590f77677c0eb908ad3a8fd8b75f",
      "name" : "Visi Calc",
      "permissions" : [

      ],
      "readmeURL" : "https://github.com/Visi-Calc/App/releases/download/0.0.37/README.md#d5c5689d94bd40e4fd31b49f1e8a6e87cc9992ffe9b31114b133d57925535d6d",
      "sha256" : "43841499d299d2bf7aa617cd14df2026c4f7c0a95be9d6c1eefe265e6a6883ca",
      "size" : 4734574,
      "stats" : {
        "coreSize" : 152608,
        "downloadCount" : 8,
        "impressionCount" : 569,
        "issueCount" : 0,
        "starCount" : 0,
        "viewCount" : 32,
        "watcherCount" : 0
      },
      "subtitle" : "A business app for business-folk",
      "version" : "0.0.37",
      "versionDate" : "2022-01-24T00:00:00Z",
      "versionDescription" : "Release 0.0.37"
    },
    {
      "beta" : true,
      "bundleIdentifier" : "app.Yankee-Swap",
      "categories" : [

      ],
      "developerName" : "fairapps <fairapps@appfair.net>",
      "downloadURL" : "https://github.com/Yankee-Swap/App/releases/download/0.0.11/Yankee-Swap-macOS.zip",
      "fundingLinks" : [

      ],
      "iconURL" : "https://github.com/Yankee-Swap/App/releases/download/0.0.11/Yankee-Swap.png",
      "localizedDescription" : "Old-time horse trading",
      "metadataURL" : "https://github.com/Yankee-Swap/App/releases/download/0.0.11/Info.plist#96efd2114846d6428e591a08296559254a988bab06ef4f2ec4518fe41dd2ed05",
      "name" : "Yankee Swap",
      "permissions" : [

      ],
      "readmeURL" : "https://github.com/Yankee-Swap/App/releases/download/0.0.11/README.md#5f665b7ecc017cdcd7917a881e68502b9062036dcc7caa1dddf81d644721debb",
      "screenshotURLs" : [
        "https://github.com/Yankee-Swap/App/releases/download/0.0.11/screenshot_01-mac-dark-mac-924x1384.png"
      ],
      "sha256" : "939c72e726019d26d6d225dd5a6d3d099a7aa662e65b82ff91ce268acb5e40a7",
      "size" : 2378046,
      "stats" : {
        "coreSize" : 68360,
        "downloadCount" : 4,
        "impressionCount" : 1143,
        "issueCount" : 0,
        "starCount" : 0,
        "viewCount" : 34,
        "watcherCount" : 0
      },
      "subtitle" : "Old-time horse trading",
      "tintColor" : "3C82C1",
      "version" : "0.0.11",
      "versionDate" : "2022-01-24T00:00:00Z",
      "versionDescription" : "Release 0.0.11"
    }
  ],
  "fundingSources" : [

  ],
  "identifier" : "net.appfair.fairapps-macos",
  "name" : "Fair Apps",
  "news" : [
    {
      "appID" : "app.Main-Course",
      "caption" : "Main Course 0.0.16 released",
      "date" : "2022-07-20T06:39:21Z",
      "identifier" : "release-app.Main-Course-0.0.16",
      "title" : "New Release: Main Course 0.0.16"
    },
    {
      "appID" : "app.Hex-Loupe",
      "caption" : "Hex Loupe 0.0.20 released",
      "date" : "2022-07-20T06:56:31Z",
      "identifier" : "release-app.Hex-Loupe-0.0.20",
      "title" : "New Release: Hex Loupe 0.0.20"
    },
    {
      "appID" : "app.Lottie-Motion",
      "caption" : "Lottie Motion updated from 0.0.87 to 0.0.90",
      "date" : "2022-07-20T07:20:15Z",
      "identifier" : "release-app.Lottie-Motion-0.0.90",
      "title" : "New Release: Lottie Motion 0.0.90"
    },
    {
      "appID" : "app.Stanza-Redux",
      "caption" : "Stanza Redux updated from 0.3.35 to 0.3.38",
      "date" : "2022-07-20T07:20:15Z",
      "identifier" : "release-app.Stanza-Redux-0.3.38",
      "title" : "New Release: Stanza Redux 0.3.38"
    },
    {
      "appID" : "app.Tune-Out",
      "caption" : "Tune Out updated from 0.8.442 to 0.8.446",
      "date" : "2022-07-20T07:20:15Z",
      "identifier" : "release-app.Tune-Out-0.8.446",
      "title" : "New Release: Tune Out 0.8.446"
    },
    {
      "appID" : "app.App-Fair",
      "caption" : "App Fair updated from 0.8.83 to 0.8.84",
      "date" : "2022-07-21T20:23:50Z",
      "identifier" : "release-app.App-Fair-0.8.84",
      "title" : "New Release: App Fair 0.8.84"
    },
    {
      "appID" : "app.Cloud-Cuckoo",
      "caption" : "Cloud Cuckoo updated from 0.9.137 to 0.9.138",
      "date" : "2022-07-21T22:17:05Z",
      "identifier" : "release-app.Cloud-Cuckoo-0.9.138",
      "title" : "New Release: Cloud Cuckoo 0.9.138"
    }
  ],
  "platform" : "macos"
}